django_future/__init__.py
django_future/admin.py
django_future/apps.py
django_future/jobs.py
django_future/models.py
django_future/utils.py
django_future/management/__init__.py
django_future/management/commands/__init__.py
django_future/management/commands/runscheduledjobs.py
django_future/migrations/0001_initial.py
django_future/migrations/0002_populate_mailing_refs.py
django_future/migrations/0003_unique_content_type_and_object_id.py
django_future/migrations/__init__.py
django_future_fork-0.5.2.dist-info/LICENSE
django_future_fork-0.5.2.dist-info/METADATA
django_future_fork-0.5.2.dist-info/WHEEL
django_future_fork-0.5.2.dist-info/top_level.txt
django_future_fork-0.5.2.dist-info/RECORD
