Metadata-Version: 2.1
Name: django-future-fork
Version: 0.5.2
Summary: Scheduled jobs in Django
Author: Smart.pr
Author-email: Shrubbery Software <team@shrubberysoft.com>, Gintautas Miliauskas <team@shrubberysoft.com>, Adomas Paltanavičius <team@shrubberysoft.com>, Maciek Szczesniak <team@shrubberysoft.com>, Jannis Leidel <team@shrubberysoft.com>
License: Copyright (c) 2009 Shrubbery Software
Project-URL: Repository, https://github.com/smartpr/django-future
Classifier: Development Status :: 4 - Beta
Classifier: License :: OSI Approved :: MIT License
Classifier: Framework :: Django
Classifier: Programming Language :: Python :: 3
Requires-Python: >=3.8
License-File: LICENSE
Requires-Dist: Django >=3.2
Requires-Dist: django-picklefield >=3.2
